MANIFEST.in
setup.cfg
setup.py
requirements/base.txt
requirements/dev.txt
table_writer.egg-info/PKG-INFO
table_writer.egg-info/SOURCES.txt
table_writer.egg-info/dependency_links.txt
table_writer.egg-info/top_level.txt
xls_writer/__init__.py
xls_writer/api.py
xls_writer/csv_formatter.py
xls_writer/detail.py
xls_writer/exceptions.py
xls_writer/field.py
xls_writer/utils.py