Metadata-Version: 1.0
Name: table-writer
Version: 0.1.1
Summary: A simple utility to format tabular data from python objects.
Home-page: UNKNOWN
Author: Jacek Bzdak
Author-email: jacek@askesis.pl
License: MIT
Platform: UNKNOWN
